astreum/__init__.py
astreum/node.py
astreum/communication/__init__.py
astreum/communication/difficulty.py
astreum/communication/disconnect.py
astreum/communication/incoming_queue.py
astreum/communication/message_pow.py
astreum/communication/node.py
astreum/communication/outgoing_queue.py
astreum/communication/setup.py
astreum/communication/util.py
astreum/communication/handlers/__init__.py
astreum/communication/handlers/handshake.py
astreum/communication/handlers/object_request.py
astreum/communication/handlers/object_response.py
astreum/communication/handlers/ping.py
astreum/communication/handlers/route_request.py
astreum/communication/handlers/route_response.py
astreum/communication/models/__init__.py
astreum/communication/models/message.py
astreum/communication/models/peer.py
astreum/communication/models/ping.py
astreum/communication/models/route.py
astreum/communication/processors/__init__.py
astreum/communication/processors/incoming.py
astreum/communication/processors/outgoing.py
astreum/communication/processors/peer.py
astreum/consensus/__init__.py
astreum/consensus/block/__init__.py
astreum/consensus/block/verify/__init__.py
astreum/consensus/block/verify/head.py
astreum/consensus/block/verify/transactions.py
astreum/consensus/fork/model.py
astreum/consensus/fork/node.py
astreum/consensus/fork/verify.py
astreum/consensus/verification/node.py
astreum/consensus/verification/worker.py
astreum/crypto/__init__.py
astreum/crypto/chacha20poly1305.py
astreum/crypto/ed25519.py
astreum/crypto/quadratic_form.py
astreum/crypto/wesolowski.py
astreum/crypto/x25519.py
astreum/machine/__init__.py
astreum/machine/parser.py
astreum/machine/tokenizer.py
astreum/machine/evaluations/__init__.py
astreum/machine/evaluations/high_evaluation.py
astreum/machine/evaluations/low_evaluation.py
astreum/machine/evaluations/script_evaluation.py
astreum/machine/models/__init__.py
astreum/machine/models/environment.py
astreum/machine/models/expression.py
astreum/machine/models/meter.py
astreum-0.3.68.dist-info/licenses/LICENSE
astreum-0.3.68.dist-info/METADATA
astreum-0.3.68.dist-info/WHEEL
astreum-0.3.68.dist-info/top_level.txt
astreum-0.3.68.dist-info/RECORD
