Metadata-Version: 2.4
Name: astreum
Version: 0.3.68
Summary: Python library to interact with the Astreum blockchain and its virtual machine.
Author-email: "Roy R. O. Okello" <roy@stelar.xyz>
Project-URL: Homepage, https://github.com/astreum/lib-py
Project-URL: Issues, https://github.com/astreum/lib-py/issues
Classifier: Programming Language :: Python :: 3
Classifier: License :: OSI Approved :: MIT License
Classifier: Operating System :: OS Independent
Requires-Python: >=3.8
License-File: LICENSE
Requires-Dist: pycryptodomex==3.21.0
Requires-Dist: cryptography==44.0.2
Requires-Dist: blake3==1.0.4
Dynamic: license-file
